atlasai/streamlit/auth/__init__.py
atlasai/streamlit/auth/auth0_service.py
atlasai/streamlit/auth/guard.py
streamlit_auth0_service-0.0.11.dist-info/METADATA
streamlit_auth0_service-0.0.11.dist-info/WHEEL
streamlit_auth0_service-0.0.11.dist-info/top_level.txt
streamlit_auth0_service-0.0.11.dist-info/RECORD
